{
    "beam_diameter": "1.0", 
    "cleanup_duration": 30.0, 
    "commit": "aad54b0bb745050e70e28c535871e5519ba35f54", 
    "extract_device": "Fusions CO2", 
    "extract_duration": 30.0, 
    "extract_units": "", 
    "extract_value": 3.0, 
    "pattern": "triangle.lp", 
    "positions": [
        {
            "is_degas": false, 
            "position": "184", 
            "x": null, 
            "y": null, 
            "z": null
        }
    ], 
    "ramp_duration": 0.0, 
    "ramp_rate": 0.0, 
    "request": "", 
    "response": "", 
    "sblob": "", 
    "tray": "", 
    "weight": 0.0
}