{
    "beam_diameter": "1.0", 
    "cleanup_duration": 30.0, 
    "commit": "41e5d3c6c88337a89eac0a306e02ad63620034c1", 
    "extract_device": "Fusions CO2", 
    "extract_duration": 30.0, 
    "extract_units": "", 
    "extract_value": 3.0, 
    "pattern": "triangle.lp", 
    "positions": [
        {
            "is_degas": false, 
            "position": "188", 
            "x": null, 
            "y": null, 
            "z": null
        }
    ], 
    "ramp_duration": 0.0, 
    "ramp_rate": 0.0, 
    "request": "", 
    "response": "", 
    "sblob": "", 
    "tray": "", 
    "weight": 0.0
}